{"GlobalPropertiesHash":"ftz4vl8CK/pvpW9lj46/jeX3pbgI4r6apTi4Kb8a19Q=","FingerprintPatternsHash":"gq3WsqcKBUGTSNle7RKKyXRIwh7M8ccEqOqYvIzoM04=","PropertyOverridesHash":"8ZRc1sGeVrPBx4lD717BgRaQekyh78QKV9SKsdt638U=","InputHashes":["M5VlNlnN96qHAlNlEU7LJYOmWuQdh2yBDToDKabCf0Q=","hnY34zqQeyYs/u7CKtq1mWE9E3QFjeE6Bkshw2VNqVY=","C/fhlmY2zDCTFqnYEZGwJEESEt\u002BobekYxguZ0tYDtgs=","8zpzFG5FnDPd8ludSIiQd/63XkLbAVKWJOVZjIbOqJ8=","CFzCnEPoynwFKYab69PQoYS88ERAlVl7DNLpKSDC5fU=","gbyScCe/QfNlQQGvTXbPf5u8qLQBeO/LI6J9lSMS3Xg="],"CachedAssets":{"M5VlNlnN96qHAlNlEU7LJYOmWuQdh2yBDToDKabCf0Q=":{"Identity":"C:\\Users\\prashant\\Downloads\\MedicineTrackerFull\\wwwroot\\app.js","SourceId":"MedicineTracker","SourceType":"Discovered","ContentRoot":"C:\\Users\\prashant\\Downloads\\MedicineTrackerFull\\wwwroot\\","BasePath":"/","RelativePath":"app#[.{fingerprint}]?.js","AssetKind":"All","AssetMode":"All","AssetRole":"Primary","AssetMergeBehavior":null,"AssetMergeSource":"","RelatedAsset":null,"AssetTraitName":null,"AssetTraitValue":null,"Fingerprint":"e96eklwf1j","Integrity":"ziAxCCbTfyP9MbZmXYXpGN01voqqaGsBbM8EU/99sfE=","CopyToOutputDirectory":"Never","CopyToPublishDirectory":"PreserveNewest","OriginalItemSpec":"wwwroot\\app.js","FileLength":1085,"LastWriteTime":"2026-07-11T07:42:27.0315431+00:00"},"hnY34zqQeyYs/u7CKtq1mWE9E3QFjeE6Bkshw2VNqVY=":{"Identity":"C:\\Users\\prashant\\Downloads\\MedicineTrackerFull\\wwwroot\\index.html","SourceId":"MedicineTracker","SourceType":"Discovered","ContentRoot":"C:\\Users\\prashant\\Downloads\\MedicineTrackerFull\\wwwroot\\","BasePath":"/","RelativePath":"index#[.{fingerprint}]?.html","AssetKind":"All","AssetMode":"All","AssetRole":"Primary","AssetMergeBehavior":null,"AssetMergeSource":"","RelatedAsset":null,"AssetTraitName":null,"AssetTraitValue":null,"Fingerprint":"wsld1rq3h0","Integrity":"oPxVsBLeT/8V\u002BFcCPyDE4oMS1C7xm65V\u002BpvbxNCuB\u002BE=","CopyToOutputDirectory":"Never","CopyToPublishDirectory":"PreserveNewest","OriginalItemSpec":"wwwroot\\index.html","FileLength":697,"LastWriteTime":"2026-07-11T07:44:30.2263486+00:00"},"C/fhlmY2zDCTFqnYEZGwJEESEt\u002BobekYxguZ0tYDtgs=":{"Identity":"C:\\Users\\prashant\\Downloads\\MedicineTrackerFull\\wwwroot\\styles.css","SourceId":"MedicineTracker","SourceType":"Discovered","ContentRoot":"C:\\Users\\prashant\\Downloads\\MedicineTrackerFull\\wwwroot\\","BasePath":"/","RelativePath":"styles#[.{fingerprint}]?.css","AssetKind":"All","AssetMode":"All","AssetRole":"Primary","AssetMergeBehavior":null,"AssetMergeSource":"","RelatedAsset":null,"AssetTraitName":null,"AssetTraitValue":null,"Fingerprint":"yqug0tqga6","Integrity":"VsyB58TCqqib16JSA5Wie4hE1IKeWpgp7HNrVGD59X0=","CopyToOutputDirectory":"Never","CopyToPublishDirectory":"PreserveNewest","OriginalItemSpec":"wwwroot\\styles.css","FileLength":197,"LastWriteTime":"2026-07-11T07:46:16.9987848+00:00"}},"CachedCopyCandidates":{}}